PyHydro/__init__.py
PyHydro/dadosgerais.py
PyHydro/fcf.py
PyHydro/hidr.py
PyHydro/interc.py
PyHydro/mddh.py
PyHydro/planerg.py
PyHydro/pmo.py
PyHydro/resequiv.py
PyHydro/submercado.py
PyHydro/term.py
py_hydro-0.0.9.dist-info/LICENSE.txt
py_hydro-0.0.9.dist-info/METADATA
py_hydro-0.0.9.dist-info/WHEEL
py_hydro-0.0.9.dist-info/top_level.txt
py_hydro-0.0.9.dist-info/RECORD
